dolfi_python_sdk-1.0.0.dist-info/licenses/LICENSE
dolfi_sdk/__init__.py
dolfi_sdk/async_client.py
dolfi_sdk/client.py
dolfi_sdk/constants.py
dolfi_sdk/exceptions.py
dolfi_sdk/models.py
dolfi_sdk/py.typed
dolfi_python_sdk-1.0.0.dist-info/METADATA
dolfi_python_sdk-1.0.0.dist-info/WHEEL
dolfi_python_sdk-1.0.0.dist-info/top_level.txt
dolfi_python_sdk-1.0.0.dist-info/RECORD
