Metadata-Version: 2.4
Name: dolfi-python-sdk
Version: 1.0.0
Summary: Python SDK for the Dolfi API - search and web scraping made simple
Home-page: https://github.com/dolfi/dolfi-python-sdk
Author: Dolfi SDK Team
Author-email: Dolfi SDK Team <support@dolfi.com>
Maintainer-email: Dolfi SDK Team <support@dolfi.com>
License: MIT
Project-URL: Homepage, https://dolfi.com
Project-URL: Documentation, https://docs.dolfi.com
Project-URL: Repository, https://github.com/dolfi/dolfi-python-sdk
Project-URL: Bug Tracker, https://github.com/dolfi/dolfi-python-sdk/issues
Keywords: dolfi,api,sdk,search,web scraping,scraping,web,content extraction,ai search,natural language search
Classifier: Development Status :: 5 - Production/Stable
Classifier: Intended Audience :: Developers
Classifier: License :: OSI Approved :: MIT License
Classifier: Operating System :: OS Independent
Classifier: Programming Language :: Python :: 3
Classifier: Programming Language :: Python :: 3.8
Classifier: Programming Language :: Python :: 3.9
Classifier: Programming Language :: Python :: 3.10
Classifier: Programming Language :: Python :: 3.11
Classifier: Programming Language :: Python :: 3.12
Classifier: Topic :: Internet :: WWW/HTTP :: Indexing/Search
Classifier: Topic :: Software Development :: Libraries :: Python Modules
Classifier: Topic :: Text Processing :: Markup :: HTML
Requires-Python: >=3.8
License-File: LICENSE
Requires-Dist: pydantic>=2.0.0
Requires-Dist: requests>=2.25.0
Requires-Dist: aiohttp>=3.8.0
Provides-Extra: dev
Requires-Dist: pytest>=7.0.0; extra == "dev"
Requires-Dist: pytest-asyncio>=0.21.0; extra == "dev"
Requires-Dist: pytest-cov>=4.0.0; extra == "dev"
Requires-Dist: black>=22.0.0; extra == "dev"
Requires-Dist: isort>=5.10.0; extra == "dev"
Requires-Dist: flake8>=4.0.0; extra == "dev"
Requires-Dist: mypy>=1.0.0; extra == "dev"
Requires-Dist: pre-commit>=2.20.0; extra == "dev"
Provides-Extra: docs
Requires-Dist: sphinx>=5.0.0; extra == "docs"
Requires-Dist: sphinx-rtd-theme>=1.0.0; extra == "docs"
Requires-Dist: myst-parser>=0.18.0; extra == "docs"
Dynamic: author
Dynamic: home-page
Dynamic: license-file
Dynamic: requires-python
